{
  "count": 2207,
  "uniques": 167,
  "clones": [
    {
      "timestamp": "2022-06-10T00:00:00Z",
      "count": 110,
      "uniques": 50
    },
    {
      "timestamp": "2022-06-11T00:00:00Z",
      "count": 167,
      "uniques": 58
    },
    {
      "timestamp": "2022-06-12T00:00:00Z",
      "count": 177,
      "uniques": 66
    },
    {
      "timestamp": "2022-06-13T00:00:00Z",
      "count": 158,
      "uniques": 72
    },
    {
      "timestamp": "2022-06-14T00:00:00Z",
      "count": 150,
      "uniques": 67
    },
    {
      "timestamp": "2022-06-15T00:00:00Z",
      "count": 160,
      "uniques": 73
    },
    {
      "timestamp": "2022-06-16T00:00:00Z",
      "count": 159,
      "uniques": 62
    },
    {
      "timestamp": "2022-06-17T00:00:00Z",
      "count": 158,
      "uniques": 60
    },
    {
      "timestamp": "2022-06-18T00:00:00Z",
      "count": 173,
      "uniques": 62
    },
    {
      "timestamp": "2022-06-19T00:00:00Z",
      "count": 171,
      "uniques": 70
    },
    {
      "timestamp": "2022-06-20T00:00:00Z",
      "count": 156,
      "uniques": 61
    },
    {
      "timestamp": "2022-06-21T00:00:00Z",
      "count": 145,
      "uniques": 59
    },
    {
      "timestamp": "2022-06-22T00:00:00Z",
      "count": 144,
      "uniques": 68
    },
    {
      "timestamp": "2022-06-23T00:00:00Z",
      "count": 143,
      "uniques": 70
    },
    {
      "timestamp": "2022-06-24T00:00:00Z",
      "count": 36,
      "uniques": 32
    }
  ]
}
