{
  "count": 2337,
  "uniques": 211,
  "clones": [
    {
      "timestamp": "2022-10-09T00:00:00Z",
      "count": 33,
      "uniques": 28
    },
    {
      "timestamp": "2022-10-10T00:00:00Z",
      "count": 175,
      "uniques": 82
    },
    {
      "timestamp": "2022-10-11T00:00:00Z",
      "count": 169,
      "uniques": 70
    },
    {
      "timestamp": "2022-10-12T00:00:00Z",
      "count": 172,
      "uniques": 71
    },
    {
      "timestamp": "2022-10-13T00:00:00Z",
      "count": 161,
      "uniques": 74
    },
    {
      "timestamp": "2022-10-14T00:00:00Z",
      "count": 179,
      "uniques": 74
    },
    {
      "timestamp": "2022-10-15T00:00:00Z",
      "count": 162,
      "uniques": 68
    },
    {
      "timestamp": "2022-10-16T00:00:00Z",
      "count": 175,
      "uniques": 71
    },
    {
      "timestamp": "2022-10-17T00:00:00Z",
      "count": 161,
      "uniques": 81
    },
    {
      "timestamp": "2022-10-18T00:00:00Z",
      "count": 164,
      "uniques": 73
    },
    {
      "timestamp": "2022-10-19T00:00:00Z",
      "count": 170,
      "uniques": 88
    },
    {
      "timestamp": "2022-10-20T00:00:00Z",
      "count": 167,
      "uniques": 87
    },
    {
      "timestamp": "2022-10-21T00:00:00Z",
      "count": 161,
      "uniques": 71
    },
    {
      "timestamp": "2022-10-22T00:00:00Z",
      "count": 167,
      "uniques": 77
    },
    {
      "timestamp": "2022-10-23T00:00:00Z",
      "count": 121,
      "uniques": 62
    }
  ]
}
